cfdpre/__init__.py
cfdpre/main.py
cfdpre-0.2.4.dist-info/METADATA
cfdpre-0.2.4.dist-info/WHEEL
cfdpre-0.2.4.dist-info/top_level.txt
cfdpre-0.2.4.dist-info/RECORD
