Metadata-Version: 2.1
Name: cfdpre
Version: 0.2.4
Summary: CFD PreProcessing Library
Author: Pushkar Sheth
Author-email: siglyserdev@gmail.com
Requires-Dist: numpy
Requires-Dist: CoolProp
